nnrunner/__init__.py
nnrunner/class.py
nnrunner/main.py
nnrunner/new.py
nnrunner-0.0.6.dist-info/METADATA
nnrunner-0.0.6.dist-info/WHEEL
nnrunner-0.0.6.dist-info/top_level.txt
nnrunner-0.0.6.dist-info/RECORD
